Workbook

Sheet Resumen
A1: Matriz de riesgos ICARO actualizada
A2: Fecha de actualización: 2026-05-01
A3: Base de actualización | B3: Casos de uso CU-00 a CU-12, HU-01 a HU-26, historias técnicas, plan de sprints 5-11 y revisión del programa entregado.
A4: Criterio aplicado | B4: Se excluyen riesgos que ya cuentan con evidencia técnica suficiente y se mantienen solo riesgos activos, parciales o pendientes.
A6: Indicador | B6: Valor | C6: Interpretación | E6: Distribución por nivel | F6: Cantidad
A7: Total de riesgos activos | B7: =COUNTA(Matriz_Riesgos!A2:A29) -> 28 | C7: Riesgos que requieren seguimiento desde sprint 5 en adelante. | E7: Crítica | F7: =COUNTIF(Matriz_Riesgos!N2:N29,"Crítica") -> 11
A8: Riesgos prioridad I | B8: =COUNTIF(Matriz_Riesgos!O2:O29,"I") -> 11 | C8: Atención inmediata por impacto crítico o exposición elevada. | E8: Alta | F8: =COUNTIF(Matriz_Riesgos!N2:N29,"Alta") -> 1
A9: Riesgos prioridad II | B9: =COUNTIF(Matriz_Riesgos!O2:O29,"II") -> 1 | C9: Planificar mitigación dentro del sprint correspondiente. | E9: Moderada | F9: =COUNTIF(Matriz_Riesgos!N2:N29,"Moderada") -> 16
A10: Riesgos prioridad III | B10: =COUNTIF(Matriz_Riesgos!O2:O29,"III") -> 16 | C10: Seguimiento controlado y respuesta preventiva. | E10: Baja | F10: =COUNTIF(Matriz_Riesgos!N2:N29,"Baja") -> 0
A11: Riesgos prioridad IV | B11: =COUNTIF(Matriz_Riesgos!O2:O29,"IV") -> 0 | C11: Aceptación o monitoreo básico.
A13: Principales focos de riesgo | B13: Backend funcional incompleto; integración frontend/API/BD; offline real; Storage/Queue/Notification; cierre contable; planillas PDF; pruebas E2E; SUS y P95.

Sheet Escalas
A1: Escalas y criterios de evaluación
A3: Escala de impacto | E3: Escala de probabilidad
A4: Nivel | B4: Puntaje | C4: Descripción | E4: Nivel | F4: Puntaje | G4: Descripción
A5: Leve | B5: 1 | C5: Afecta ajustes puntuales o actividades no críticas. | E5: Baja | F5: 1 | G5: Puede presentarse de forma poco frecuente.
A6: Moderado | B6: 2 | C6: Incide en coordinación, acceso, documentación o consistencia parcial. | E6: Media | F6: 2 | G6: Puede ocurrir bajo condiciones operativas o técnicas específicas.
A7: Alto | B7: 3 | C7: Afecta entregables sustantivos, integración o calidad del sistema. | E7: Alta | F7: 3 | G7: Tiene condiciones favorables para ocurrir en el proyecto.
A8: Crítico | B8: 4 | C8: Puede comprometer alcance, integridad, validación o entrega funcional.
A10: Regla de exposición
A11: Exposición | B11: Nivel | C11: Prioridad | D11: Criterio de respuesta
A12: 9 a 12 | B12: Crítica | C12: I | D12: Atención inmediata y seguimiento por sprint.
A13: 7 a 8 | B13: Alta | C13: II | D13: Mitigación planificada y responsable definido.
A14: 4 a 6 | B14: Moderada | C14: III | D14: Control preventivo y seguimiento periódico.
A15: 1 a 3 | B15: Baja | C15: IV | D15: Aceptación controlada o monitoreo básico.

Sheet Matriz_Riesgos
A1: Código | B1: Riesgo identificado | C1: Categoría | D1: Fase / sprint principal | E1: HU/CU/RF afectados | F1: Evidencia utilizada | G1: Impacto resumido | H1: Detonante / señal de alerta | I1: Impacto | J1: Puntaje impacto | K1: Probabilidad | L1: Puntaje probabilidad | M1: Exposición | N1: Nivel exposición | O1: Prioridad | P1: Estrategia principal | Q1: Respuesta planificada | R1: Medida de contingencia | S1: Responsable sugerido | T1: Estado actualizado | U1: Observaciones
A2: R1 | B2: Backend funcional incompleto para módulos de avances, compras, inventario, contabilidad, reportes y planillas. | C2: Técnico / Integración | D2: Sprints 5-11 | E2: HU-01, HU-05, HU-08, HU-09, HU-11, HU-12, HU-13, HU-14, HU-23 | F2: En server.js solo están activas /auth, /users y /proyectos; rutas /avances, /compras y /reportes aparecen comentadas, sin rutas de inventario ni cierres. | G2: Impide demostrar flujos completos con persistencia real y expone una brecha entre documentación y producto. | H2: Intentar ejecutar pruebas funcionales completas y encontrar módulos sin endpoints reales. | I2: Crítico | J2: =IF(I2="Leve",1,IF(I2="Moderado",2,IF(I2="Alto",3,IF(I2="Crítico",4,0)))) -> 4 | K2: Alta | L2: =IF(K2="Baja",1,IF(K2="Media",2,IF(K2="Alta",3,0))) -> 3 | M2: =J2*L2 -> 12 | N2: =IF(M2>=9,"Crítica",IF(M2>=7,"Alta",IF(M2>=4,"Moderada","Baja"))) -> Crítica | O2: =IF(N2="Crítica","I",IF(N2="Alta","II",IF(N2="Moderada","III","IV"))) -> I | P2: Mitigación prioritaria | Q2: Implementar rutas, controladores y servicios mínimos para avances, compras, inventario, cierres, reportes y planillas, priorizando los criterios críticos de HU actualizadas. | R2: Acotar alcance demostrable y documentar módulos no integrados como pendientes técnicos si no alcanzan a implementarse. | S2: Equipo backend / responsable técnico | T2: Activo | U2: Debe abordarse antes de una campaña integral de pruebas.
A3: R2 | B3: Frontend con cobertura visual amplia, pero con dependencia de datos mock en módulos funcionales. | C3: Integración / Calidad | D3: Sprints 5-11 | E3: HU-01 a HU-18, HU-23, HU-24 | F3: El frontend contiene múltiples vistas y componentes, pero no se evidencia consumo real de API para los módulos de negocio. | G3: Puede generar falsa percepción de avance funcional porque las pantallas existen, pero no prueban persistencia ni reglas reales. | H3: Las pruebas navegan pantallas correctamente, pero los datos no cambian en PostgreSQL. | I3: Crítico | J3: =IF(I3="Leve",1,IF(I3="Moderado",2,IF(I3="Alto",3,IF(I3="Crítico",4,0)))) -> 4 | K3: Alta | L3: =IF(K3="Baja",1,IF(K3="Media",2,IF(K3="Alta",3,0))) -> 3 | M3: =J3*L3 -> 12 | N3: =IF(M3>=9,"Crítica",IF(M3>=7,"Alta",IF(M3>=4,"Moderada","Baja"))) -> Crítica | O3: =IF(N3="Crítica","I",IF(N3="Alta","II",IF(N3="Moderada","III","IV"))) -> I | P3: Mitigación | Q3: Sustituir mocks críticos por servicios API reales empezando por obra, compras, inventario y contabilidad. | R3: Mantener mocks solo para demostración visual y separar explícitamente evidencia frontend de evidencia funcional. | S3: Equipo frontend / backend | T3: Activo | U3: Riesgo central de integración.
A4: R3 | B4: Capa offline móvil no implementada como PWA/local cache/sincronización real. | C4: Disponibilidad / Offline | D4: Sprint 5 y Sprint 9 | E4: HU-01, HU-03, HU-04, HU-09, HU-22 | F4: package.json del frontend no incluye idb ni vite-plugin-pwa; existen componentes visuales de sincronización, pero no se evidencia motor offline real. | G4: El sistema no garantiza operación en campo sin conectividad ni sincronización posterior verificable. | H4: Modo sin red no conserva operaciones reales o no las sincroniza contra API. | I4: Crítico | J4: =IF(I4="Leve",1,IF(I4="Moderado",2,IF(I4="Alto",3,IF(I4="Crítico",4,0)))) -> 4 | K4: Alta | L4: =IF(K4="Baja",1,IF(K4="Media",2,IF(K4="Alta",3,0))) -> 3 | M4: =J4*L4 -> 12 | N4: =IF(M4>=9,"Crítica",IF(M4>=7,"Alta",IF(M4>=4,"Moderada","Baja"))) -> Crítica | O4: =IF(N4="Crítica","I",IF(N4="Alta","II",IF(N4="Moderada","III","IV"))) -> I | P4: Mitigación prioritaria | Q4: Implementar IndexedDB, cola local, estados Pendiente/Sincronizado/Error y Sync Manager conectado a la API. | R4: Reducir offline a prototipo controlado y declarar limitación si no se completa integración real. | S4: Equipo frontend móvil / backend | T4: Activo | U4: Afecta directamente HU-22 y disponibilidad en campo.
A5: R4 | B5: StorageService para evidencias y planillas no implementado en backend. | C5: Infraestructura / Archivos | D5: Sprint 5 y Sprint 11 | E5: HU-03, HU-04, HU-13, HU-14 | F5: El esquema contiene campos url/storageKey, pero no se observa servicio backend de almacenamiento para imágenes o PDFs. | G5: Las evidencias y planillas no pueden almacenarse ni recuperarse de forma persistente y trazable. | H5: Subida de archivo o consulta de PDF falla o queda simulada. | I5: Alto | J5: =IF(I5="Leve",1,IF(I5="Moderado",2,IF(I5="Alto",3,IF(I5="Crítico",4,0)))) -> 3 | K5: Alta | L5: =IF(K5="Baja",1,IF(K5="Media",2,IF(K5="Alta",3,0))) -> 3 | M5: =J5*L5 -> 9 | N5: =IF(M5>=9,"Crítica",IF(M5>=7,"Alta",IF(M5>=4,"Moderada","Baja"))) -> Crítica | O5: =IF(N5="Crítica","I",IF(N5="Alta","II",IF(N5="Moderada","III","IV"))) -> I | P5: Mitigación | Q5: Crear StorageService con validación de formato/tamaño, generación de nombre único y registro de URL o referencia persistente. | R5: Usar almacenamiento local controlado para prototipo y documentar limitación cloud. | S5: Equipo backend | T5: Activo | U5: Debe cubrir evidencias y planillas.
A6: R5 | B6: QueueService para planillas PDF pesadas no implementado. | C6: Infraestructura / Procesamiento diferido | D6: Sprint 11 | E6: HU-13 | F6: No se evidencia cola de tareas ni worker para generación diferida de PDF. | G6: La generación de planillas con evidencias puede bloquear la respuesta HTTP o fallar por tiempo de procesamiento. | H6: Planilla con muchas evidencias tarda demasiado o produce timeout. | I6: Alto | J6: =IF(I6="Leve",1,IF(I6="Moderado",2,IF(I6="Alto",3,IF(I6="Crítico",4,0)))) -> 3 | K6: Media | L6: =IF(K6="Baja",1,IF(K6="Media",2,IF(K6="Alta",3,0))) -> 2 | M6: =J6*L6 -> 6 | N6: =IF(M6>=9,"Crítica",IF(M6>=7,"Alta",IF(M6>=4,"Moderada","Baja"))) -> Moderada | O6: =IF(N6="Crítica","I",IF(N6="Alta","II",IF(N6="Moderada","III","IV"))) -> III | P6: Mitigación | Q6: Implementar cola simple de generación con estados Pendiente, En proceso, Completado y Error. | R6: Limitar volumen de evidencias por planilla y procesar solo planillas ligeras de forma síncrona. | S6: Equipo backend | T6: Activo | U6: Relacionado con PDF y notificaciones.
A7: R6 | B7: NotificationService no implementado para aprobaciones, rechazos, requerimientos y planillas. | C7: Infraestructura / Comunicación funcional | D7: Sprint 6, 7 y 11 | E7: HU-05, HU-06, HU-07, HU-13 | F7: No se observa servicio backend de notificaciones; las historias actualizadas lo requieren como soporte funcional. | G7: Los usuarios no reciben avisos de eventos críticos y deben depender de consulta manual. | H7: Aprobaciones o planillas listas no notifican al usuario creador o solicitante. | I7: Moderado | J7: =IF(I7="Leve",1,IF(I7="Moderado",2,IF(I7="Alto",3,IF(I7="Crítico",4,0)))) -> 2 | K7: Alta | L7: =IF(K7="Baja",1,IF(K7="Media",2,IF(K7="Alta",3,0))) -> 3 | M7: =J7*L7 -> 6 | N7: =IF(M7>=9,"Crítica",IF(M7>=7,"Alta",IF(M7>=4,"Moderada","Baja"))) -> Moderada | O7: =IF(N7="Crítica","I",IF(N7="Alta","II",IF(N7="Moderada","III","IV"))) -> III | P7: Mitigación | Q7: Implementar notificación interna básica y dejar parametrizable correo para fase posterior. | R7: Registrar avisos en bandeja del sistema sin envío externo. | S7: Equipo backend / frontend | T7: Activo | U7: Debe evitarse sobredimensionar correo real si no hay tiempo.
A8: R7 | B8: Modelo de datos no cubre completamente consumo, movimientos de inventario y órdenes de cambio. | C8: Datos / Dominio | D8: Sprints 7-9 | E8: HU-02, HU-08, HU-09, HU-10 | F8: schema.prisma incluye InventarioProyecto, pero no se evidencia entidad ConsumoMaterial, MovimientoInventario u OrdenCambio formal. | G8: Puede impedir trazabilidad completa de salidas, Kardex, validación de excedentes y autorización de avances fuera de presupuesto. | H8: No es posible reconstruir entradas/salidas o validar excedentes con soporte persistido. | I8: Crítico | J8: =IF(I8="Leve",1,IF(I8="Moderado",2,IF(I8="Alto",3,IF(I8="Crítico",4,0)))) -> 4 | K8: Alta | L8: =IF(K8="Baja",1,IF(K8="Media",2,IF(K8="Alta",3,0))) -> 3 | M8: =J8*L8 -> 12 | N8: =IF(M8>=9,"Crítica",IF(M8>=7,"Alta",IF(M8>=4,"Moderada","Baja"))) -> Crítica | O8: =IF(N8="Crítica","I",IF(N8="Alta","II",IF(N8="Moderada","III","IV"))) -> I | P8: Mitigación prioritaria | Q8: Agregar entidades mínimas para consumo, movimientos de inventario y autorización de cambio presupuestario o formalizar su exclusión. | R8: Usar audit_log y campos de inventario como soporte temporal, documentando limitación. | S8: Equipo de datos / backend | T8: Activo | U8: Afecta inventario y control presupuestario.
A9: R8 | B9: Inmutabilidad de audit_log no está protegida a nivel de base de datos. | C9: Auditoría / Seguridad | D9: Sprint 10-11 | E9: HU-24, RNF auditoría | F9: Existe AuditLog y AuditService, pero no se observan triggers de bloqueo UPDATE/DELETE sobre audit_log. | G9: Un acceso directo a BD podría alterar o eliminar evidencia de auditoría. | H9: Actualización o eliminación manual de audit_log desde herramienta de administración. | I9: Alto | J9: =IF(I9="Leve",1,IF(I9="Moderado",2,IF(I9="Alto",3,IF(I9="Crítico",4,0)))) -> 3 | K9: Media | L9: =IF(K9="Baja",1,IF(K9="Media",2,IF(K9="Alta",3,0))) -> 2 | M9: =J9*L9 -> 6 | N9: =IF(M9>=9,"Crítica",IF(M9>=7,"Alta",IF(M9>=4,"Moderada","Baja"))) -> Moderada | O9: =IF(N9="Crítica","I",IF(N9="Alta","II",IF(N9="Moderada","III","IV"))) -> III | P9: Mitigación | Q9: Agregar migración con triggers/funciones que bloqueen UPDATE y DELETE sobre audit_log. | R9: Restringir permisos de usuario de BD y documentar control manual. | S9: Equipo backend / base de datos | T9: Activo | U9: El riesgo es parcial, porque la auditoría base sí existe.
A10: R9 | B10: Auditoría automática genérica puede ser insuficiente para datos antes/después y eventos críticos. | C10: Auditoría / Trazabilidad | D10: Sprints 7-11 | E10: HU-06, HU-07, HU-08, HU-09, HU-12, HU-13, HU-24 | F10: audit.middleware registra body posterior, pero no garantiza snapshot real de datos antes/después en operaciones de dominio. | G10: Puede limitar la reconstrucción de decisiones críticas y cambios de estado. | H10: Consulta de auditoría no permite explicar quién cambió qué estado y cuál era el valor anterior. | I10: Alto | J10: =IF(I10="Leve",1,IF(I10="Moderado",2,IF(I10="Alto",3,IF(I10="Crítico",4,0)))) -> 3 | K10: Media | L10: =IF(K10="Baja",1,IF(K10="Media",2,IF(K10="Alta",3,0))) -> 2 | M10: =J10*L10 -> 6 | N10: =IF(M10>=9,"Crítica",IF(M10>=7,"Alta",IF(M10>=4,"Moderada","Baja"))) -> Moderada | O10: =IF(N10="Crítica","I",IF(N10="Alta","II",IF(N10="Moderada","III","IV"))) -> III | P10: Mitigación | Q10: Complementar auditoría genérica con logs explícitos en servicios críticos de aprobación, recepción, consumo, cierre y planillas. | R10: Registrar datos mínimos obligatorios por evento si no se implementan snapshots completos. | S10: Equipo backend | T10: Activo | U10: Clave para HU-24.
A11: R10 | B11: Gestión de proyectos incompleta en backend. | C11: Configuración / Backend | D11: Sprint 5 y Sprint 6 | E11: HU-15, HU-20, HU-21 | F11: proyectos.routes.js permite listar y consultar detalle, pero no se evidencia creación, edición, activación/desactivación ni asignaciones administrativas completas. | G11: No se pueden cumplir HU-15, HU-20 y HU-21 de forma transaccional. | H11: Administrador no puede crear/editar proyectos reales mediante API. | I11: Alto | J11: =IF(I11="Leve",1,IF(I11="Moderado",2,IF(I11="Alto",3,IF(I11="Crítico",4,0)))) -> 3 | K11: Media | L11: =IF(K11="Baja",1,IF(K11="Media",2,IF(K11="Alta",3,0))) -> 2 | M11: =J11*L11 -> 6 | N11: =IF(M11>=9,"Crítica",IF(M11>=7,"Alta",IF(M11>=4,"Moderada","Baja"))) -> Moderada | O11: =IF(N11="Crítica","I",IF(N11="Alta","II",IF(N11="Moderada","III","IV"))) -> III | P11: Mitigación | Q11: Agregar endpoints POST/PUT/PATCH para proyectos y endpoints de asignaciones usuario-proyecto-vigencia. | R11: Cargar proyectos por seed y documentar limitación administrativa. | S11: Equipo backend | T11: Activo | U11: Los sprints 1-4 no se modifican; se regulariza desde sprint 5.
A12: R11 | B12: Catálogo de materiales sin API administrativa real. | C12: Configuración / Inventario | D12: Sprint 6 | E12: HU-05, HU-08, HU-09, HU-10, HU-26 | F12: El frontend contiene componentes de materiales, pero no se observan rutas backend /materiales o /catalogos. | G12: Requerimientos, recepciones y consumos pueden quedar sin fuente real de materiales vigentes. | H12: El usuario intenta seleccionar o crear materiales y solo encuentra datos simulados. | I12: Alto | J12: =IF(I12="Leve",1,IF(I12="Moderado",2,IF(I12="Alto",3,IF(I12="Crítico",4,0)))) -> 3 | K12: Media | L12: =IF(K12="Baja",1,IF(K12="Media",2,IF(K12="Alta",3,0))) -> 2 | M12: =J12*L12 -> 6 | N12: =IF(M12>=9,"Crítica",IF(M12>=7,"Alta",IF(M12>=4,"Moderada","Baja"))) -> Moderada | O12: =IF(N12="Crítica","I",IF(N12="Alta","II",IF(N12="Moderada","III","IV"))) -> III | P12: Mitigación | Q12: Implementar CRUD mínimo de materiales con estado activo/inactivo y validación de duplicados. | R12: Usar seed de materiales fijos y limitar administración del catálogo. | S12: Equipo backend / frontend | T12: Activo | U12: Necesario para HU-26.
A13: R12 | B13: Carga masiva de rubros no garantizada con rollback real en backend. | C13: Configuración / Carga masiva | D13: Sprint 5-6 | E13: HU-16 | F13: Hay componentes frontend de CSV, pero no se observa endpoint backend de importación transaccional. | G13: Puede ocurrir carga parcial o inconsistente de rubros frente a errores de archivo. | H13: CSV con error genera algunos rubros guardados y otros rechazados sin reversión completa. | I13: Alto | J13: =IF(I13="Leve",1,IF(I13="Moderado",2,IF(I13="Alto",3,IF(I13="Crítico",4,0)))) -> 3 | K13: Media | L13: =IF(K13="Baja",1,IF(K13="Media",2,IF(K13="Alta",3,0))) -> 2 | M13: =J13*L13 -> 6 | N13: =IF(M13>=9,"Crítica",IF(M13>=7,"Alta",IF(M13>=4,"Moderada","Baja"))) -> Moderada | O13: =IF(N13="Crítica","I",IF(N13="Alta","II",IF(N13="Moderada","III","IV"))) -> III | P13: Mitigación | Q13: Implementar endpoint de importación CSV con validación de cabecera, tipos, duplicados y transacción atómica. | R13: Reducir carga a validación manual y registro individual si no se implementa importación completa. | S13: Equipo backend | T13: Activo | U13: Debe mantener la cabecera exacta definida.
... A29: R28 | B29: Falta de evidencia end-to-end Frontend → API → PostgreSQL para flujos críticos. | C29: Integración / Evidencia | D29: Sprints 5-11 | E29: HU-01, HU-05, HU-08, HU-09, HU-12, HU-13, HU-24 | F29: El programa contiene backend parcial y frontend amplio; faltan recorridos integrados documentados con capturas/logs/BD. | G29: La defensa puede no probar que el sistema funciona más allá del prototipo visual. | H29: No se cuenta con evidencia de una operación real persistida y auditada de inicio a fin. | I29: Crítico | J29: =IF(I29="Leve",1,IF(I29="Moderado",2,IF(I29="Alto",3,IF(I29="Crítico",4,0)))) -> 4 | K29: Alta | L29: =IF(K29="Baja",1,IF(K29="Media",2,IF(K29="Alta",3,0))) -> 3 | M29: =J29*L29 -> 12 | N29: =IF(M29>=9,"Crítica",IF(M29>=7,"Alta",IF(M29>=4,"Moderada","Baja"))) -> Crítica | O29: =IF(N29="Crítica","I",IF(N29="Alta","II",IF(N29="Moderada","III","IV"))) -> I | P29: Mitigación prioritaria | Q29: Definir 5 flujos E2E mínimos: login, avance+evidencia, requerimiento+aprobación, recepción+consumo, cierre+planilla. | R29: Si un flujo no está completo, documentar evidencia parcial y brecha técnica con plan de corrección. | S29: Equipo QA / desarrollo | T29: Activo | U29: Debe alimentar informe de ejecución actualizado.

Sheet Respuesta_Priorizada
A1: Código | B1: Prioridad | C1: Riesgo priorizado | D1: Estrategia principal | E1: Acción preventiva / respuesta | F1: Medida de contingencia | G1: Responsable sugerido | H1: Fase / sprint | I1: Estado
A2: R1 | B2: =VLOOKUP(A2,Matriz_Riesgos!A:O,15,FALSE) -> I | C2: Backend funcional incompleto para módulos de avances, compras, inventario, contabilidad, reportes y planillas. | D2: Mitigación prioritaria | E2: Implementar rutas, controladores y servicios mínimos para avances, compras, inventario, cierres, reportes y planillas, priorizando los criterios críticos de HU actualizadas. | F2: Acotar alcance demostrable y documentar módulos no integrados como pendientes técnicos si no alcanzan a implementarse. | G2: Equipo backend / responsable técnico | H2: Sprints 5-11 | I2: Activo
A3: R2 | B3: =VLOOKUP(A3,Matriz_Riesgos!A:O,15,FALSE) -> I | C3: Frontend con cobertura visual amplia, pero con dependencia de datos mock en módulos funcionales. | D3: Mitigación | E3: Sustituir mocks críticos por servicios API reales empezando por obra, compras, inventario y contabilidad. | F3: Mantener mocks solo para demostración visual y separar explícitamente evidencia frontend de evidencia funcional. | G3: Equipo frontend / backend | H3: Sprints 5-11 | I3: Activo
A4: R3 | B4: =VLOOKUP(A4,Matriz_Riesgos!A:O,15,FALSE) -> I | C4: Capa offline móvil no implementada como PWA/local cache/sincronización real. | D4: Mitigación prioritaria | E4: Implementar IndexedDB, cola local, estados Pendiente/Sincronizado/Error y Sync Manager conectado a la API. | F4: Reducir offline a prototipo controlado y declarar limitación si no se completa integración real. | G4: Equipo frontend móvil / backend | H4: Sprint 5 y Sprint 9 | I4: Activo
A5: R7 | B5: =VLOOKUP(A5,Matriz_Riesgos!A:O,15,FALSE) -> I | C5: Modelo de datos no cubre completamente consumo, movimientos de inventario y órdenes de cambio. | D5: Mitigación prioritaria | E5: Agregar entidades mínimas para consumo, movimientos de inventario y autorización de cambio presupuestario o formalizar su exclusión. | F5: Usar audit_log y campos de inventario como soporte temporal, documentando limitación. | G5: Equipo de datos / backend | H5: Sprints 7-9 | I5: Activo
A6: R13 | B6: =VLOOKUP(A6,Matriz_Riesgos!A:O,15,FALSE) -> I | C6: Flujo de requerimientos de compra sin backend completo. | D6: Mitigación prioritaria | E6: Activar módulo de compras con endpoints para creación, detalle, aprobación, rechazo y notificación. | F6: Mantener flujo simulado como evidencia visual, separándolo de la evidencia funcional. | G6: Equipo backend / frontend | H6: Sprints 6-7 | I6: Activo
A7: R14 | B7: =VLOOKUP(A7,Matriz_Riesgos!A:O,15,FALSE) -> I | C7: Recepción, consumo y consulta de inventario sin backend transaccional. | D7: Mitigación prioritaria | E7: Implementar servicios transaccionales de recepción, consumo y consulta de inventario por proyecto. | F7: Limitar pruebas a un escenario manual controlado y documentar ausencia de Kardex real. | G7: Equipo backend / datos | H7: Sprints 8-9 | I7: Activo
A8: R15 | B8: =VLOOKUP(A8,Matriz_Riesgos!A:O,15,FALSE) -> I | C8: Cierre contable, bloqueo de registros y hash sin implementación backend completa. | D8: Mitigación prioritaria | E8: Implementar motor de consolidación/cierre con validación de pendientes, hash, bloqueo y rollback ante fallas. | F8: Mostrar consolidación como prototipo y dejar cierre real como limitación técnica documentada. | G8: Equipo backend / contabilidad | H8: Sprint 10 | I8: Activo
A9: R16 | B9: =VLOOKUP(A9,Matriz_Riesgos!A:O,15,FALSE) -> II | C9: Generación y consulta de planillas PDF sin backend ni procesamiento real. | D9: Mitigación | E9: Implementar generación mínima de PDF basada en cierre, guardar referencia y permitir consulta/descarga. | F9: Generar reporte HTML exportable manualmente y documentar limitación del PDF. | G9: Equipo backend / reportes | H9: Sprint 11 | I9: Activo
A10: R18 | B10: =VLOOKUP(A10,Matriz_Riesgos!A:O,15,FALSE) -> I | C10: Pruebas automatizadas limitadas a seguridad, sin cobertura de módulos de negocio. | D10: Mitigación | E10: Agregar pruebas mínimas de integración para flujos críticos por sprint desde el sprint 5. | F10: Ejecutar pruebas manuales documentadas con evidencia si no se automatiza todo. | G10: Equipo QA / desarrollo | H10: Sprints 5-11 | I10: Activo
A11: R20 | B11: =VLOOKUP(A11,Matriz_Riesgos!A:O,15,FALSE) -> III | C11: RNF de rendimiento P95, disponibilidad y fiabilidad sin medición verificable. | D11: Mitigación | E11: Definir prueba ligera de rendimiento sobre endpoints principales y registrar resultados. | F11: Reportar medición parcial por módulo y justificar limitaciones del entorno. | G11: Equipo QA / backend | H11: Sprint 11 | I11: Activo
A12: R21 | B12: =VLOOKUP(A12,Matriz_Riesgos!A:O,15,FALSE) -> III | C12: Replanificación concentrada desde sprint 5 por congelamiento de los sprints 1 al 4. | D12: Mitigación | E12: Mantener tareas combinadas, priorizar flujos núcleo y reservar pruebas críticas por sprint. | F12: Reducir funcionalidades no esenciales y conservar trazabilidad documental del ajuste. | G12: Equipo del proyecto | H12: Sprints 5-11 | I12: Activo
A13: R22 | B13: =VLOOKUP(A13,Matriz_Riesgos!A:O,15,FALSE) -> III | C13: Pérdida de trazabilidad entre casos de uso, historias actualizadas, historias técnicas, pruebas y sprint plan. | D13: Mitigación | E13: Mantener matriz CU-HU-HT-Pruebas actualizada y usar un único identificador por historia. | F13: Agregar anexo de cambios y correcciones de trazabilidad antes de la entrega. | G13: Responsable documental / técnico | H13: Sprints 5-11 | I13: Activo
... A15: R28 | B15: =VLOOKUP(A15,Matriz_Riesgos!A:O,15,FALSE) -> I | C15: Falta de evidencia end-to-end Frontend → API → PostgreSQL para flujos críticos. | D15: Mitigación prioritaria | E15: Definir 5 flujos E2E mínimos: login, avance+evidencia, requerimiento+aprobación, recepción+consumo, cierre+planilla. | F15: Si un flujo no está completo, documentar evidencia parcial y brecha técnica con plan de corrección. | G15: Equipo QA / desarrollo | H15: Sprints 5-11 | I15: Activo

Sheet Seguimiento
A1: Fecha de revisión | B1: Código del riesgo | C1: Riesgo | D1: Sprint / fase | E1: Probabilidad anterior | F1: Probabilidad nueva | G1: Impacto anterior | H1: Impacto nuevo | I1: Nivel anterior | J1: Nivel nuevo | K1: Estado | L1: Responsable | M1: Acción tomada | N1: Próxima revisión | O1: Observaciones
B2: R1 | C2: Backend funcional incompleto para módulos de avances, compras, inventario, contabilidad, reportes y planillas. | D2: Sprints 5-11 | E2: Alta | G2: Crítico | I2: =VLOOKUP(B2,Matriz_Riesgos!A:N,14,FALSE) -> Crítica | K2: Activo | L2: Equipo backend / responsable técnico
B3: R2 | C3: Frontend con cobertura visual amplia, pero con dependencia de datos mock en módulos funcionales. | D3: Sprints 5-11 | E3: Alta | G3: Crítico | I3: =VLOOKUP(B3,Matriz_Riesgos!A:N,14,FALSE) -> Crítica | K3: Activo | L3: Equipo frontend / backend
B4: R3 | C4: Capa offline móvil no implementada como PWA/local cache/sincronización real. | D4: Sprint 5 y Sprint 9 | E4: Alta | G4: Crítico | I4: =VLOOKUP(B4,Matriz_Riesgos!A:N,14,FALSE) -> Crítica | K4: Activo | L4: Equipo frontend móvil / backend
B5: R4 | C5: StorageService para evidencias y planillas no implementado en backend. | D5: Sprint 5 y Sprint 11 | E5: Alta | G5: Alto | I5: =VLOOKUP(B5,Matriz_Riesgos!A:N,14,FALSE) -> Crítica | K5: Activo | L5: Equipo backend
B6: R5 | C6: QueueService para planillas PDF pesadas no implementado. | D6: Sprint 11 | E6: Media | G6: Alto | I6: =VLOOKUP(B6,Matriz_Riesgos!A:N,14,FALSE) -> Moderada | K6: Activo | L6: Equipo backend
B7: R6 | C7: NotificationService no implementado para aprobaciones, rechazos, requerimientos y planillas. | D7: Sprint 6, 7 y 11 | E7: Alta | G7: Moderado | I7: =VLOOKUP(B7,Matriz_Riesgos!A:N,14,FALSE) -> Moderada | K7: Activo | L7: Equipo backend / frontend
B8: R7 | C8: Modelo de datos no cubre completamente consumo, movimientos de inventario y órdenes de cambio. | D8: Sprints 7-9 | E8: Alta | G8: Crítico | I8: =VLOOKUP(B8,Matriz_Riesgos!A:N,14,FALSE) -> Crítica | K8: Activo | L8: Equipo de datos / backend
B9: R8 | C9: Inmutabilidad de audit_log no está protegida a nivel de base de datos. | D9: Sprint 10-11 | E9: Media | G9: Alto | I9: =VLOOKUP(B9,Matriz_Riesgos!A:N,14,FALSE) -> Moderada | K9: Activo | L9: Equipo backend / base de datos
B10: R9 | C10: Auditoría automática genérica puede ser insuficiente para datos antes/después y eventos críticos. | D10: Sprints 7-11 | E10: Media | G10: Alto | I10: =VLOOKUP(B10,Matriz_Riesgos!A:N,14,FALSE) -> Moderada | K10: Activo | L10: Equipo backend
B11: R10 | C11: Gestión de proyectos incompleta en backend. | D11: Sprint 5 y Sprint 6 | E11: Media | G11: Alto | I11: =VLOOKUP(B11,Matriz_Riesgos!A:N,14,FALSE) -> Moderada | K11: Activo | L11: Equipo backend
B12: R11 | C12: Catálogo de materiales sin API administrativa real. | D12: Sprint 6 | E12: Media | G12: Alto | I12: =VLOOKUP(B12,Matriz_Riesgos!A:N,14,FALSE) -> Moderada | K12: Activo | L12: Equipo backend / frontend
B13: R12 | C13: Carga masiva de rubros no garantizada con rollback real en backend. | D13: Sprint 5-6 | E13: Media | G13: Alto | I13: =VLOOKUP(B13,Matriz_Riesgos!A:N,14,FALSE) -> Moderada | K13: Activo | L13: Equipo backend
... B29: R28 | C29: Falta de evidencia end-to-end Frontend → API → PostgreSQL para flujos críticos. | D29: Sprints 5-11 | E29: Alta | G29: Crítico | I29: =VLOOKUP(B29,Matriz_Riesgos!A:N,14,FALSE) -> Crítica | K29: Activo | L29: Equipo QA / desarrollo
